ufdata/__init__.py
ufdata/document.py
ufdata/note.py
ufdata/pitch.py
ufdata/project.py
ufdata/tempo.py
ufdata/time_signature.py
ufdata/track.py
utaformatix_data-1.0.0.dist-info/METADATA
utaformatix_data-1.0.0.dist-info/WHEEL
utaformatix_data-1.0.0.dist-info/top_level.txt
utaformatix_data-1.0.0.dist-info/RECORD
