Metadata-Version: 2.1
Name: utaformatix-data
Version: 1.0.0
Summary: Common data container for singing synthesis softwares.
Home-page: https://github.com/sdercolin/utaformatix-data
Author: sdercolin
Author-email: sder.colin@gmail.com
License: Apache-2.0 license
Platform: UNKNOWN
Requires-Dist: pyhumps (>=3.8.0)
